<?xml version="1.0" encoding="UTF-8"?><record_update table="sc_cat_item_category">
    <sc_cat_item_category action="INSERT_OR_UPDATE">
        <sc_cat_item display_value="臨時テスト用">49369d8453285290a32fd2a0a0490e1c</sc_cat_item>
        <sc_category display_value="臨時カテゴリ">53d6d98853285290a32fd2a0a0490ef7</sc_category>
        <sys_class_name>sc_cat_item_category</sys_class_name>
        <sys_created_by>admin</sys_created_by>
        <sys_created_on>2024-09-05 03:51:54</sys_created_on>
        <sys_id>3feb9d8853685290a32fd2a0a0490ee1</sys_id>
        <sys_mod_count>0</sys_mod_count>
        <sys_name>臨時カテゴリ.臨時テスト用</sys_name>
        <sys_package display_value="NeedIt" source="x_58872_needit">6ead8e780f603200cd674f8ce1050ed1</sys_package>
        <sys_policy/>
        <sys_scope display_value="NeedIt">6ead8e780f603200cd674f8ce1050ed1</sys_scope>
        <sys_update_name>sc_cat_item_category_3feb9d8853685290a32fd2a0a0490ee1</sys_update_name>
        <sys_updated_by>admin</sys_updated_by>
        <sys_updated_on>2024-09-05 03:51:54</sys_updated_on>
    </sc_cat_item_category>
</record_update>
